pixelflow/__init__.py
pixelflow/buffer.py
pixelflow/colors.py
pixelflow/crossings.py
pixelflow/media.py
pixelflow/slicer.py
pixelflow/smoother.py
pixelflow/strategies.py
pixelflow/timer.py
pixelflow/validators.py
pixelflow/zones.py
pixelflow/annotators/__init__.py
pixelflow/annotators/anchors.py
pixelflow/annotators/blur.py
pixelflow/annotators/box.py
pixelflow/annotators/crossing.py
pixelflow/annotators/dot.py
pixelflow/annotators/filled_box.py
pixelflow/annotators/fps_counter.py
pixelflow/annotators/grid_overlay.py
pixelflow/annotators/heatmap.py
pixelflow/annotators/keypoint.py
pixelflow/annotators/keypoint_skeleton.py
pixelflow/annotators/label.py
pixelflow/annotators/mask.py
pixelflow/annotators/motion_dots.py
pixelflow/annotators/motion_trails.py
pixelflow/annotators/oval.py
pixelflow/annotators/pixelate.py
pixelflow/annotators/polygon.py
pixelflow/annotators/scale_bar.py
pixelflow/annotators/utils.py
pixelflow/annotators/zones.py
pixelflow/detections/__init__.py
pixelflow/detections/converters.py
pixelflow/detections/detections.py
pixelflow/detections/filters.py
pixelflow/tracker/__init__.py
pixelflow/tracker/bytetrack.py
pixelflow/tracker/kalman_filter.py
pixelflow/tracker/matching.py
pixelflow/tracker/track.py
pixelflow/transforms/__init__.py
pixelflow/transforms/detections.py
pixelflow/transforms/image.py
pixelflow/transforms/inverse.py
pixelflow-0.1.2.dist-info/licenses/LICENSE
pixelflow-0.1.2.dist-info/METADATA
pixelflow-0.1.2.dist-info/WHEEL
pixelflow-0.1.2.dist-info/top_level.txt
pixelflow-0.1.2.dist-info/RECORD
