Metadata-Version: 2.4
Name: pixelflow
Version: 0.1.2
Summary: Computer vision processing library for visualizing and analyzing detection results from ML models
Author-email: Emrah Nazif <emrah@datamarkin.com>, Datamarkin <support@datamarkin.com>
License: MIT
Project-URL: Homepage, https://github.com/datamarkin/pixelflow
Project-URL: Repository, https://github.com/datamarkin/pixelflow
Project-URL: Issues, https://github.com/datamarkin/pixelflow/issues
Project-URL: Documentation, https://pixelflow.datamarkin.com
Keywords: computer-vision,visualization,annotation,post-processing,tracking,opencv,yolo,detectron2,ml-results
Classifier: Development Status :: 3 - Alpha
Classifier: Intended Audience :: Developers
Classifier: Intended Audience :: Science/Research
Classifier: License :: OSI Approved :: MIT License
Classifier: Operating System :: OS Independent
Classifier: Programming Language :: Python :: 3
Classifier: Programming Language :: Python :: 3.9
Classifier: Programming Language :: Python :: 3.10
Classifier: Programming Language :: Python :: 3.11
Classifier: Programming Language :: Python :: 3.12
Classifier: Topic :: Scientific/Engineering :: Artificial Intelligence
Classifier: Topic :: Scientific/Engineering :: Image Recognition
Classifier: Topic :: Software Development :: Libraries :: Python Modules
Requires-Python: >=3.9
License-File: LICENSE
Requires-Dist: shapely>=2.0.0
Requires-Dist: numpy>=1.21.0
Requires-Dist: opencv-python>=4.8.0
Requires-Dist: scipy>=1.10.0
Provides-Extra: dev
Requires-Dist: pytest>=7.0.0; extra == "dev"
Requires-Dist: pytest-cov>=4.0.0; extra == "dev"
Requires-Dist: pytest-mock>=3.10.0; extra == "dev"
Dynamic: license-file
